LICENSE
MANIFEST.in
README.md
setup.py
libpythonprodihl/__init__.py
libpythonprodihl/github_api.py
libpythonprodihl.egg-info/PKG-INFO
libpythonprodihl.egg-info/SOURCES.txt
libpythonprodihl.egg-info/dependency_links.txt
libpythonprodihl.egg-info/not-zip-safe
libpythonprodihl.egg-info/requires.txt
libpythonprodihl.egg-info/top_level.txt
libpythonprodihl/__pycache__/__init__.cpython-39.pyc
libpythonprodihl/__pycache__/github_api.cpython-39.pyc